surrogates/__init__.py
surrogates/tests/__init__.py
surrogates/tests/test_codec.py
surrogates-1.0.2.dist-info/COPYING
surrogates-1.0.2.dist-info/METADATA
surrogates-1.0.2.dist-info/WHEEL
surrogates-1.0.2.dist-info/top_level.txt
surrogates-1.0.2.dist-info/RECORD
