Metadata-Version: 2.1
Name: surrogates
Version: 1.0.2
Summary: Encode and decode pairs of surrogate characters
Home-page: https://github.com/hartwork/surrogates
Author: Sebastian Pipping
Author-email: sebastian@pipping.org
License: MIT
Platform: UNKNOWN
Classifier: Development Status :: 4 - Beta
Classifier: License :: OSI Approved :: MIT License
Classifier: Intended Audience :: Developers
Classifier: Programming Language :: Python
Classifier: Programming Language :: Python :: 3
Classifier: Programming Language :: Python :: 3 :: Only
Classifier: Programming Language :: Python :: 3.5
Classifier: Programming Language :: Python :: 3.6
Classifier: Programming Language :: Python :: 3.7
Classifier: Programming Language :: Python :: 3.8
Classifier: Topic :: Text Processing
Requires-Python: >=3.5
